snake_amh/__about__.py
snake_amh/__init__.py
snake_amh/entry_points.py
snake_amh/snake.py
snake_amh/snake.tcss
snake_amh-0.0.2.dist-info/METADATA
snake_amh-0.0.2.dist-info/WHEEL
snake_amh-0.0.2.dist-info/entry_points.txt
snake_amh-0.0.2.dist-info/licenses/LICENSE.txt
snake_amh-0.0.2.dist-info/RECORD
