Metadata-Version: 2.4
Name: snake-amh
Version: 0.0.2
Project-URL: Documentation, https://github.com/andrewhall1124/snake-amh#readme
Project-URL: Issues, https://github.com/andrewhall1124/snake-amh/issues
Project-URL: Source, https://github.com/andrewhall1124/snake-amh
Author-email: andrewhall1124 <andrewmartinhall2@gmail.com>
License-Expression: MIT
License-File: LICENSE.txt
Classifier: Development Status :: 4 - Beta
Classifier: Programming Language :: Python
Classifier: Programming Language :: Python :: 3.8
Classifier: Programming Language :: Python :: 3.9
Classifier: Programming Language :: Python :: 3.10
Classifier: Programming Language :: Python :: 3.11
Classifier: Programming Language :: Python :: 3.12
Classifier: Programming Language :: Python :: Implementation :: CPython
Classifier: Programming Language :: Python :: Implementation :: PyPy
Requires-Python: >=3.8
Requires-Dist: textual>=0.73.0
